.gitignore
.pre-commit-config.yaml
.pylintrc
.readthedocs.yaml
CODE_OF_CONDUCT.md
LICENSE
README.rst
README.rst.license
pyproject.toml
requirements.txt
setup.py
sparkfun_qwiicquadsolidstaterelay.py
.github/PULL_REQUEST_TEMPLATE/adafruit_circuitpython_pr.md
.github/workflows/build.yml
.github/workflows/failure-help-text.yml
.github/workflows/release.yml
LICENSES/CC-BY-4.0.txt
LICENSES/MIT.txt
LICENSES/Unlicense.txt
circuitpython_sparkfun_qwiicquadsolidstaterelay.egg-info/PKG-INFO
circuitpython_sparkfun_qwiicquadsolidstaterelay.egg-info/SOURCES.txt
circuitpython_sparkfun_qwiicquadsolidstaterelay.egg-info/dependency_links.txt
circuitpython_sparkfun_qwiicquadsolidstaterelay.egg-info/requires.txt
circuitpython_sparkfun_qwiicquadsolidstaterelay.egg-info/top_level.txt
docs/api.rst
docs/api.rst.license
docs/conf.py
docs/examples.rst
docs/examples.rst.license
docs/index.rst
docs/index.rst.license
docs/requirements.txt
docs/_static/favicon.ico
docs/_static/favicon.ico.license
examples/sparkfun_qwiicquadsolidstaterelay_simpletest.py