Metadata-Version: 2.1
Name: circuitpython-sparkfun-qwiicquadsolidstaterelay
Version: 1.0.6
Summary: CircuitPython library for the Sparkfun Quad Solid State Qwiic Relay
Home-page: https://github.com/gbeland/CircuitPython_Sparkfun_QwiicQuadSolidStateRelay.git
Author: Graham Beland
Author-email: gbeland@gmail.com
License: MIT
Keywords: adafruit blinka circuitpython micropython sparkfun_qwiicquadsolidstaterelay power i2c iot qwuuc original sparkfun relay quad solid state qwiic stemma blinkaCircuit kit 16833 kit-16833
Classifier: Development Status :: 3 - Alpha
Classifier: Intended Audience :: Developers
Classifier: Topic :: Software Development :: Libraries
Classifier: Topic :: System :: Hardware
Classifier: License :: OSI Approved :: MIT License
Classifier: Programming Language :: Python :: 3
License-File: LICENSE
